MANIFEST.in
README.rst
setup.py
nctime/__init__.py
nctime/nctcck.py
nctime/nctxck.py
nctime.egg-info/PKG-INFO
nctime.egg-info/SOURCES.txt
nctime.egg-info/dependency_links.txt
nctime.egg-info/entry_points.txt
nctime.egg-info/requires.txt
nctime.egg-info/top_level.txt
nctime/axis/__init__.py
nctime/axis/constants.py
nctime/axis/context.py
nctime/axis/custom_exceptions.py
nctime/axis/handler.py
nctime/axis/main.py
nctime/overlap/__init__.py
nctime/overlap/constants.py
nctime/overlap/context.py
nctime/overlap/custom_exceptions.py
nctime/overlap/handler.py
nctime/overlap/main.py
nctime/utils/__init__.py
nctime/utils/collector.py
nctime/utils/constants.py
nctime/utils/context.py
nctime/utils/custom_exceptions.py
nctime/utils/custom_print.py
nctime/utils/help.py
nctime/utils/misc.py
nctime/utils/parser.py
nctime/utils/time.py