Metadata-Version: 1.1
Name: nctime
Version: 4.6.0
Summary: Diagnoses netCDF time axis.
Home-page: https://github.com/Prodiguer/nctime
Author: Levavasseur Guillaume
Author-email: glipsl@ipsl.fr
License: UNKNOWN
Platform: UNKNOWN
Classifier: Development Status :: 5 - Production/Stable
Classifier: Environment :: Console
Classifier: Intended Audience :: Science/Research
Classifier: Intended Audience :: System Administrators
Classifier: Natural Language :: English
Classifier: Operating System :: Unix
Classifier: Programming Language :: Python :: 2.6
Classifier: Topic :: Scientific/Engineering
Classifier: Topic :: Software Development :: Build Tools
